MANIFEST.in
README.rst
setup.py
ssdb/__init__.py
ssdb/_compat.py
ssdb/batch.py
ssdb/client.py
ssdb/connection.py
ssdb/exceptions.py
ssdb/utils.py
ssdb_py3.egg-info/PKG-INFO
ssdb_py3.egg-info/SOURCES.txt
ssdb_py3.egg-info/dependency_links.txt
ssdb_py3.egg-info/not-zip-safe
ssdb_py3.egg-info/top_level.txt