Metadata-Version: 1.1
Name: ssdb-py3
Version: 0.0.3
Summary: Python3 client for SSDB
Home-page: https://github.com/vmvz/ssdb-py3
Author: dai3
Author-email: github@dai3.com
License: BSD-2
Keywords: SSDB
Platform: UNKNOWN
Classifier: Development Status :: 5 - Production/Stable
Classifier: Environment :: Console
Classifier: Intended Audience :: Developers
Classifier: License :: OSI Approved :: BSD License
Classifier: Operating System :: OS Independent
Classifier: Programming Language :: Python
Classifier: Programming Language :: Python :: 3.6
